sqlalchemy_hero/__init__.py
sqlalchemy_hero/hero_database.py
sqlalchemy_hero/hero_generator.py
sqlalchemy_hero/hero_type_mapper.py
sqlalchemy_hero/types/__init__.py
sqlalchemy_hero/types/column.py
sqlalchemy_hero/types/file.py
sqlalchemy_hero/types/index.py
sqlalchemy_hero/types/metadata.py
sqlalchemy_hero/types/mysql_schema.py
sqlalchemy_hero/types/postgres_schema.py
sqlalchemy_hero/types/spec.py
sqlalchemy_hero/types/table.py
sqlalchemy_hero-0.1.1.dist-info/LICENSE
sqlalchemy_hero-0.1.1.dist-info/WHEEL
sqlalchemy_hero-0.1.1.dist-info/METADATA
sqlalchemy_hero-0.1.1.dist-info/RECORD
