Metadata-Version: 2.1
Name: sqlalchemy-hero
Version: 0.1.1
Summary: SchemaHero table generator from SQLAlchemy models.
Home-page: https://github.com/busykoala/sqlalchemy-hero
License: GPL-3.0-or-later
Keywords: SQLAlchemy,SchemaHero,GitOps,database,k8s
Author: Matthias Osswald
Author-email: info@busykoala.io
Requires-Python: >=3.8,<4.0
Classifier: License :: OSI Approved :: GNU General Public License v3 or later (GPLv3+)
Classifier: Programming Language :: Python :: 3
Classifier: Programming Language :: Python :: 3.10
Classifier: Programming Language :: Python :: 3.8
Classifier: Programming Language :: Python :: 3.9
Requires-Dist: PyYAML (>=6.0,<7.0)
Requires-Dist: SQLAlchemy (>=1.4,<2.0)
Requires-Dist: SQLAlchemy-Utils (>=0.38,<0.39)
Requires-Dist: arrow (>=1.2,<2.0)
Project-URL: Repository, https://github.com/busykoala/sqlalchemy-hero
